pandasfiles
pandasfiles/base
pandasfiles/conf
pandasfiles/log
pandasfiles/tmp
pandasfiles/utils
